sendbox_sdk
